ml4t/engineer/AGENT.md
ml4t/engineer/__init__.py
ml4t/engineer/_version.py
ml4t/engineer/api.py
ml4t/engineer/dataset.py
ml4t/engineer/preprocessing.py
ml4t/engineer/py.typed
ml4t/engineer/bars/AGENT.md
ml4t/engineer/bars/__init__.py
ml4t/engineer/bars/base.py
ml4t/engineer/bars/imbalance.py
ml4t/engineer/bars/run.py
ml4t/engineer/bars/tick.py
ml4t/engineer/bars/vectorized.py
ml4t/engineer/bars/volume.py
ml4t/engineer/config/__init__.py
ml4t/engineer/config/base.py
ml4t/engineer/config/experiment.py
ml4t/engineer/config/feature_config.py
ml4t/engineer/config/labeling.py
ml4t/engineer/config/preprocessing_config.py
ml4t/engineer/config/validation.py
ml4t/engineer/core/__init__.py
ml4t/engineer/core/decorators.py
ml4t/engineer/core/deprecation.py
ml4t/engineer/core/exceptions.py
ml4t/engineer/core/registry.py
ml4t/engineer/core/schemas.py
ml4t/engineer/core/types.py
ml4t/engineer/core/validation.py
ml4t/engineer/core/calendars/__init__.py
ml4t/engineer/core/calendars/base.py
ml4t/engineer/core/calendars/crypto.py
ml4t/engineer/core/calendars/equity.py
ml4t/engineer/discovery/__init__.py
ml4t/engineer/discovery/catalog.py
ml4t/engineer/features/AGENT.md
ml4t/engineer/features/__init__.py
ml4t/engineer/features/composite.py
ml4t/engineer/features/cross_asset.py
ml4t/engineer/features/fdiff.py
ml4t/engineer/features/regime.py
ml4t/engineer/features/risk.py
ml4t/engineer/features/math/AGENT.md
ml4t/engineer/features/math/__init__.py
ml4t/engineer/features/math/max.py
ml4t/engineer/features/math/min.py
ml4t/engineer/features/math/sum.py
ml4t/engineer/features/microstructure/AGENT.md
ml4t/engineer/features/microstructure/__init__.py
ml4t/engineer/features/microstructure/amihud_illiquidity.py
ml4t/engineer/features/microstructure/effective_tick_rule.py
ml4t/engineer/features/microstructure/kyle_lambda.py
ml4t/engineer/features/microstructure/order_book.py
ml4t/engineer/features/microstructure/order_flow_imbalance.py
ml4t_engineer-0.1.0a7.dist-info/METADATA
ml4t_engineer-0.1.0a7.dist-info/WHEEL
ml4t_engineer-0.1.0a7.dist-info/RECORD
