Metadata-Version: 2.4
Name: ml4t-engineer
Version: 0.1.0a7
Summary: High-performance quantitative finance feature engineering library
Project-URL: Homepage, https://github.com/stefan-jansen/ml4t-engineer
Project-URL: Documentation, https://ml4t-engineer.readthedocs.io
Project-URL: Repository, https://github.com/stefan-jansen/ml4t-engineer
Project-URL: Issues, https://github.com/stefan-jansen/ml4t-engineer/issues
Project-URL: Changelog, https://github.com/stefan-jansen/ml4t-engineer/blob/main/CHANGELOG.md
Author-email: Stefan Jansen <stefan@ml4trading.io>
Maintainer-email: Stefan Jansen <stefan@ml4trading.io>
License: MIT
Keywords: backtesting,feature-engineering,features,finance,labeling,machine-learning,microstructure,polars,quantitative-finance,technical-analysis,trading
Classifier: Development Status :: 4 - Beta
Classifier: Intended Audience :: Developers
Classifier: Intended Audience :: Financial and Insurance Industry
Classifier: Intended Audience :: Science/Research
Classifier: License :: OSI Approved :: MIT License
Classifier: Operating System :: OS Independent
Classifier: Programming Language :: Python :: 3
Classifier: Programming Language :: Python :: 3.11
Classifier: Programming Language :: Python :: 3.12
Classifier: Programming Language :: Python :: 3.13
Classifier: Topic :: Office/Business :: Financial :: Investment
Classifier: Topic :: Scientific/Engineering :: Artificial Intelligence
Classifier: Topic :: Scientific/Engineering :: Information Analysis
Classifier: Typing :: Typed
Requires-Python: >=3.11
Requires-Dist: matplotlib>=3.7.0
Requires-Dist: numba>=0.57.0
Requires-Dist: numpy<2.3,>=1.24.0
Requires-Dist: pandas>=2.0.0
Requires-Dist: polars>=0.20.0
Requires-Dist: pyarrow>=14.0.0
Requires-Dist: pydantic>=2.0.0
Requires-Dist: python-dateutil>=2.8.0
Requires-Dist: pyyaml>=6.0.0
Requires-Dist: scikit-learn>=1.3.0
Requires-Dist: scipy>=1.10.0
Requires-Dist: statsmodels>=0.14.0
Requires-Dist: structlog>=23.0.0
Provides-Extra: all
Requires-Dist: arch>=6.0.0; extra == 'all'
Requires-Dist: duckdb>=0.9.0; extra == 'all'
Requires-Dist: hypothesis>=6.80.0; extra == 'all'
Requires-Dist: ipdb>=0.13.0; extra == 'all'
Requires-Dist: ipython>=8.14.0; extra == 'all'
Requires-Dist: lightgbm>=4.0.0; extra == 'all'
Requires-Dist: matplotlib>=3.7.0; extra == 'all'
Requires-Dist: mypy>=1.5.0; extra == 'all'
Requires-Dist: myst-parser>=2.0.0; extra == 'all'
Requires-Dist: nbsphinx>=0.9.0; extra == 'all'
Requires-Dist: pandas-market-calendars>=4.0.0; extra == 'all'
Requires-Dist: plotly>=5.15.0; extra == 'all'
Requires-Dist: pre-commit>=3.3.0; extra == 'all'
Requires-Dist: pytest-benchmark>=4.0.0; extra == 'all'
Requires-Dist: pytest-cov>=4.1.0; extra == 'all'
Requires-Dist: pytest-timeout>=2.1.0; extra == 'all'
Requires-Dist: pytest-xdist>=3.3.0; extra == 'all'
Requires-Dist: pytest>=7.4.0; extra == 'all'
Requires-Dist: ruff>=0.1.0; extra == 'all'
Requires-Dist: seaborn>=0.12.0; extra == 'all'
Requires-Dist: shap>=0.44.0; extra == 'all'
Requires-Dist: sphinx-autodoc-typehints>=1.24.0; extra == 'all'
Requires-Dist: sphinx-rtd-theme>=1.3.0; extra == 'all'
Requires-Dist: sphinx>=7.0.0; extra == 'all'
Requires-Dist: ta-lib>=0.4.0; extra == 'all'
Provides-Extra: calendars
Requires-Dist: pandas-market-calendars>=4.0.0; extra == 'calendars'
Provides-Extra: dev
Requires-Dist: arch>=6.0.0; extra == 'dev'
Requires-Dist: duckdb>=0.9.0; extra == 'dev'
Requires-Dist: hypothesis>=6.80.0; extra == 'dev'
Requires-Dist: ipdb>=0.13.0; extra == 'dev'
Requires-Dist: ipython>=8.14.0; extra == 'dev'
Requires-Dist: lightgbm>=4.0.0; extra == 'dev'
Requires-Dist: mypy>=1.5.0; extra == 'dev'
Requires-Dist: pandas-market-calendars>=4.0.0; extra == 'dev'
Requires-Dist: pre-commit>=3.3.0; extra == 'dev'
Requires-Dist: pytest-benchmark>=4.0.0; extra == 'dev'
Requires-Dist: pytest-cov>=4.1.0; extra == 'dev'
Requires-Dist: pytest-timeout>=2.1.0; extra == 'dev'
Requires-Dist: pytest-xdist>=3.3.0; extra == 'dev'
Requires-Dist: pytest>=7.4.0; extra == 'dev'
Requires-Dist: ruff>=0.1.0; extra == 'dev'
Requires-Dist: shap>=0.44.0; extra == 'dev'
Requires-Dist: ta-lib>=0.4.0; extra == 'dev'
Requires-Dist: yfinance>=0.2.0; extra == 'dev'
Provides-Extra: docs
Requires-Dist: myst-parser>=2.0.0; extra == 'docs'
Requires-Dist: nbsphinx>=0.9.0; extra == 'docs'
Requires-Dist: sphinx-autodoc-typehints>=1.24.0; extra == 'docs'
Requires-Dist: sphinx-rtd-theme>=1.3.0; extra == 'docs'
Requires-Dist: sphinx>=7.0.0; extra == 'docs'
Provides-Extra: ml
Requires-Dist: lightgbm>=4.0.0; extra == 'ml'
Requires-Dist: shap>=0.44.0; extra == 'ml'
Provides-Extra: store
Requires-Dist: duckdb>=0.9.0; extra == 'store'
Provides-Extra: ta
Requires-Dist: ta-lib>=0.4.0; extra == 'ta'
Provides-Extra: viz
Requires-Dist: matplotlib>=3.7.0; extra == 'viz'
Requires-Dist: plotly>=5.15.0; extra == 'viz'
Requires-Dist: seaborn>=0.12.0; extra == 'viz'
